hintBitPack/HintBitPack.sv
`timescale 1ns / 1ps

module HintBitPack #(
    parameter K = 8,
    parameter W = 75,
    parameter COEFF_WIDTH = 256
) (
    input  logic clk,
    input  logic rst,
    input  logic startpin,
    output logic endpin,
    input  logic  h [K-1:0][255:0],
    output logic [7:0] y [W + K - 1:0]
);

    typedef enum logic [1:0] {
        IDLE, PROCESS, DONE
    } state_t;

    state_t state;
    logic [7:0] index;
    logic [$clog2(K):0] i;
    logic [$clog2(256):0] j;

    // Separate process for synchronous reset
    always_ff @(posedge clk) begin
        if (rst) begin
//            for (int idx = 0; idx < (W + K); idx++) begin
//                y[idx] <= 1'b0;
//            end
            y <= '{default: 8'h00};
            index <= 0;
            i <= 0;
            j <= 0;
            endpin <= 1'b0;
            state  <= IDLE;
        end else begin
            case (state)
                IDLE: begin
                    if (startpin) begin
                        endpin <= 0;
                        index <= 0;
                        i <= 0;
                        j <= 0;
                        y <= '{default: 8'h00};
                        state <= PROCESS;
                    end
                end
                PROCESS: begin
                    if (i < K) begin
                        if (j < 256'h100) begin
                            if (h[i][j]) begin
                                y[index] <= j[7:0];  // Assign value only in this condition
                                index <= index + 1'b1;
                            end 
                            j <= j + 1;
                        end else begin
                            y[W + i] <= index;
                            j <= 0;
                            i <= i + 1;
                        end
                    end else begin
                        state <= DONE;
                    end
                end
                DONE: begin
                    endpin <= 1;
                    if (!startpin) begin
                        state <= IDLE;
                    end
                end
            endcase
        end
    end

endmodule

hintBitPack/HintbitPack_tb.sv
`timescale 1ns / 1ps

module HintBitPack_tb;

    parameter int K = 8;
    parameter int COEFF_WIDTH = 256;
    parameter int W = 75;

    logic clk;
    logic rst;
    logic  h[K-1:0][COEFF_WIDTH-1:0];
    logic [663:0] y; //[W+K-1:0];
    logic startpin;
    logic endpin;

    HintBitPack #(
        .K(K),
//        .COEFF_WIDTH(COEFF_WIDTH),
        .W(W)
    ) uut (
        .clk(clk),
        .rst(rst),
        .h(h),
        .startpin(startpin),
        .endpin(endpin),
        .y(y)
    );
    initial begin 
    clk=1;
    rst=1;
//     h = '{
    
//     256'b0000010000000100000001000000010000000100000001000000010000000100000001000000010000000100000001000000010000000100000001000000010000000100000001000000010000000100000001000000010000000100000001000000010000000100000001000000010000000100000001000000010000000100,
//     256'b0000010000000100000001000000010000000100000001000000010000000100000001000000010000000100000001000000010000000100000001000000010000000100000001000000010000000100000001000000010000000100000001000000010000000100000001000000010000000100000001000000010000000100,
//     256'b0000000000000000000000000000000000000000000000000000000000000000000000000000000000000000000000000000000000000000000000000000000000000000000000000000000000000000000000000000000000000000000000000000000000000000000000000000000000000000000000000000011110000011,
//     256'b0000000000000000000000000000000000000000000000000000000000000000000000000000000000000000000000000000000000000000000000000000000000000000000000000000000000000000000000000000000000000000000000000000000000000000000000000000000000000000000000000000000000000100,
//     256'b0000000000000000000000000000000000000000000000000000000000000000000000000000000000000000000000000000000000000000000000000000000000000000000000000000000000000000000000000000000000000000000000000000000000000000000000000000000000000000000000000000000000000100,
//     256'b0000000000000000000000000000000000000000000000000000000000000000000000000000000000000000000000000000000000000000000000000000000000000000000000000000000000000000000000000000000000000000000000000000000000000000000000000000000000000000000000000000000000000100,
//     256'b0000000000000000000000000000000000000000000000000000000000000000000000000000000000000000000000000000000000000000000000000000000000000000000000000000000000000000000000000000000000000000000000000000000000000000000000000000000000000000000000000000000000000100,
//     256'b0000000000000000000000000000000000000000000000000000000000000000000000000000000000000000000000000000000000000000000000000000000000000000000000000000000000000000000000000000000000000000000000000000000000000000000000000000000000000000000000000000000000100000};
     startpin = 1'b0;
//    h[0] = 256'b0000010000000100000001000000010000000100000001000000010000000100000001000000010000000100000001000000010000000100000001000000010000000100000001000000010000000100000001000000010000000100000001000000010000000100000001000000010000000100000001000000010000000100;
//    //    result = lsb to msb => 2 ,10,18 26  34  42 50 58 66 74  82  90  98  106  114   122  130  138  146  154 162  170 178  186  194 202 210 218 226  234 242 250                                                                      
//    h[1] = 256'b0000010000000100000001000000010000000100000001000000010000000100000001000000010000000100000001000000010000000100000001000000010000000100000001000000010000000100000001000000010000000100000001000000010000000100000001000000010000000100000001000000010000000100;
//    h[2] = 256'b01111;
//    h[3] = 256'b010;
//    h[4] = 256'b010;
//    h[5] = 256'b010;
//    h[6] = 256'b0110;
//    h[7] = 256'b0110;
//    h = '{
//           256'b0000000000000100000001000000010000000100000001000000010000000100000001000000010000000100000001000000010000000100000001000000010000000100000001000000010000000100000001000000010000000100000001000000010000000100000001000000010000000100000001000000010000000110,
//           256'b0000010000000100000001000000010000000100000001000000010000000100000001000000010000000100000001000000010000000100000001000000010000000100000001000000010000000100000001000000010000000100000001000000010000000100000001000000010000000100000001000000010000100100,
//           256'b0000000000000000000000000000000000000000000000000000000000000000000000000000000000000000000000000000000000000000000000000000000000000000000000000000000000000000000000000000000000000000000000000000000000000000000000000000000000000000000000000000001111100000,
//           256'b0000000000000000000000000000000000000000000000000000000000000000000000000000000000000000000000000000000000000000000000000000000000000000000000000000000000000000000000000000000000000000000000000000000000000000000000000000000000000000000000001000000000000000,
//           256'b0000000000000000000000000000000000000000000000000000000000000000000000000000000000000000000000000000000000000000000000000000000000000000000000000000000000000000000000000000000000000000000000000000000000000000000000000000000000000000000000010000000000000000,
//           256'b0000000000000000000000000000000000000000000000000000000000000000000000000000000000000000000000000000000000000000000000000000000000000000000000000000000000000000000000000000000000000000000000000000000000000000000000000000000000000000000100000000000000000000,
//           256'b0000000000000000000000000000000000000000000000000000000000000000000000000000000000000000000000000000000000000000000000000000000000000000000000000000000000000000000000000000000000000000000000000000000000000000000000000000000000000000010000000000000000000000,
//           256'b0000000000000000000000000000000000000000000000000000000000000000000000000000000000000000000000000000000000000000000000000000000000000000000000000000000000000000000000000000000000000000000000000000000000000000000000000000000000000000000000000000000000100000
//       };
    #2
        rst=0;
        startpin= 1'b1;
//         h = '{
        
//         256'b0000010000000100000001000000010000000100000001000000010000000100000001000000010000000100000001000000010000000100000001000000010000000100000001000000010000000100000001000000010000000100000001000000010000000100000001000000010000000100000001000000010000000100,
//         256'b0000010000000100000001000000010000000100000001000000010000000100000001000000010000000100000001000000010000000100000001000000010000000100000001000000010000000100000001000000010000000100000001000000010000000100000001000000010000000100000001000000010000000100,
//         256'b0000000000000000000000000000000000000000000000000000000000000000000000000000000000000000000000000000000000000000000000000000000000000000000000000000000000000000000000000000000000000000000000000000000000000000000000000000000000000000000000000000011110000011,
//         256'b0000000000000000000000000000000000000000000000000000000000000000000000000000000000000000000000000000000000000000000000000000000000000000000000000000000000000000000000000000000000000000000000000000000000000000000000000000000000000000000000000000000000000100,
//         256'b0000000000000000000000000000000000000000000000000000000000000000000000000000000000000000000000000000000000000000000000000000000000000000000000000000000000000000000000000000000000000000000000000000000000000000000000000000000000000000000000000000000000000100,
//         256'b0000000000000000000000000000000000000000000000000000000000000000000000000000000000000000000000000000000000000000000000000000000000000000000000000000000000000000000000000000000000000000000000000000000000000000000000000000000000000000000000000000000000000100,
//         256'b0000000000000000000000000000000000000000000000000000000000000000000000000000000000000000000000000000000000000000000000000000000000000000000000000000000000000000000000000000000000000000000000000000000000000000000000000000000000000000000000000000000000000100,
//         256'b0000000000000000000000000000000000000000000000000000000000000000000000000000000000000000000000000000000000000000000000000000000000000000000000000000000000000000000000000000000000000000000000000000000000000000000000000000000000000000000000000000000000100000};
//h = '{
//   256'b000000000000000000000000000000000000000000000000100000000000000000000000000000000000000000000000000000000000010000000000000000001000000000000000000000000000000000000000000000000000000000100000000000000000000000000000000000000000000010000000000001000000000000,
//256'b0000000001000000000101000000000000100000000000000000000000000000000000000000000000000000000000000000000000000000000000000001000000000000000000000100000000000000000000000000000000000000000001000000000000000000000000000000000000000000010000000000000000,
//256'b0000000000000000000000010000000000111000000000000000000000000000000000000010000000000000000000000000000000000000001000000000000000000000000000000000000000000000000010000000000000000000000000000110000000001000000000000000000000000000000000000000000000000000,
//256'b0000000000000000000000000000000000000000000000000000000000000000000000000000000000000000000000000000000000010000000000001000000000000000000000000000000000000000000000000000001000010000000000000000100000001000010000000000000000000000000000000000000010000000,
//256'b00000000000000000000000000001000000000000000000000000000000000100000000010000000000000100001000000000000000000000000000000000000000000001000000000000000100000000000000010000000000000000100000000000000000000000000000000000000000000000000000000000000,
//256'b0001000000000000000001000000000000000000000000000000001000000000000000000000000000000000000000000000000010001000000000000000000000000000000000000000000000000000000000000000000000000000000000000000010000000000000000000000000000000000000000000000000000000000,
//256'b000000000000000000000000000000000010001000000000000000000000000000000000000000100000000000000000000000000001000000000000000000000000010000000000000000000001000000001000000001000000010000000000000000000000000000000000000000000000000000000000000000,
//256'b0000000000000000000000000000000000000000000000000000000100000000000000000000000000000000010000000000000000000000010000000000000000000000000000000000000000000000000000000000000000010000000000000000000000000000000000000000000010000000000000000000000100000000000000000000};
//    h='{
//    256'b0000000000000000100000000000000000000001000000000000000000000000000000000000100000000000000000000000000000000000000000000000000000000000000000100000000000000000000000100000000000000000000000000000000010000000000000000000000000000000000000000000000000000000, 256'b0000000000000000000000000000000000000000001000000010000000010000000100000000100000000000000000000000000100000000000000000010000000000000000000000000100000000000000000000000000001000000000000000000000000000000000000000100010000000000000000000000000000000000, 256'b0000000000000000000000000000000000000000000000000000000000100000000000000000000000000000000000000000000000000000000000000000000000000000000000000001000100000000000000000000000000000000000000000000000100000000000000000000000000000000001000000000000000001000, 256'b0000000000000000000000000000000000000000000000000000000000000000001000000000000000000001000000000100000000000001000000000000000000000000000000000000000000000000000010000100000000000001000000000100000000000000000000000000000000010000000000000000000000000000, 256'b0000000100000000000000000000000000000000000000100001000000010000000000000000100001000000000000000000000000000000000000000000000000000001000000000000100000000000000000000000000000000000000000000000000000000000000000000000000000000000000000000000000000000000, 256'b0000000000000000000000000000000000000000000000000001000000000110000000000000000000000000000100000000000000000000000000000000000000000000000001000000000000000000000000000000000000000100000000000000000000000000000000000001110000000000100000000000000000000000, 256'b0000000000000000010000000000000000000000000000000000000000001000000000000000000000000000000000000000000000000001000000000000000000000010000000000000000000000000000000000000000000000000000000000000000000000000000000000000010000000000001010000000001000000000, 256'b0000000000001000000000000100000000000000000000000000000000000000000001000000000000000000000000000000000000000000000000000000000100000000000000000010000000000000000000000000000000000000000000000000000000000001000000000000000000000000000000000000000000000000};
        h[0] = '{1'b0, 0, 0, 0, 0, 0, 0, 0, 0, 0, 0, 0, 0, 0, 0, 0, 0, 0, 0, 0, 0, 0, 0, 0, 0, 0, 0, 0, 0, 0, 0, 0, 0, 0, 0, 0, 0, 0, 0, 0, 0, 0, 0, 0, 0, 0, 0, 0, 1, 0, 0, 0, 0, 0, 0, 0, 0, 0, 0, 0, 0, 0, 0, 0, 0, 0, 0, 0, 0, 0, 0, 0, 0, 0, 0, 0, 0, 0, 0, 0, 0, 0, 0, 0, 0, 0, 0, 0, 0, 0, 0, 0, 0, 0, 0, 0, 0, 0, 0, 0, 0, 0, 0, 0, 0, 0, 0, 0, 0, 1, 0, 0, 0, 0, 0, 0, 0, 0, 0, 0, 0, 0, 0, 0, 0, 0, 0, 0, 1, 0, 0, 0, 0, 0, 0, 0, 0, 0, 0, 0, 0, 0, 0, 0, 0, 0, 0, 0, 0, 0, 0, 0, 0, 0, 0, 0, 0, 0, 0, 0, 0, 0, 0, 0, 0, 0, 0, 0, 0, 0, 0, 0, 0, 0, 0, 0, 0, 0, 0, 0, 0, 0, 0, 0, 0, 0, 1, 0, 0, 0, 0, 0, 0, 0, 0, 0, 0, 0, 0, 0, 0, 0, 0, 0, 0, 0, 0, 0, 0, 0, 0, 0, 0, 0, 0, 0, 0, 0, 0, 0, 0, 0, 0, 0, 0, 0, 0, 0, 0, 0, 1, 0, 0, 0, 0, 0, 0, 0, 0, 0, 0, 0, 0, 1, 0, 0, 0, 0, 0, 0, 0, 0, 0, 0, 0, 0};
        h[1] = '{0, 0, 0, 0, 0, 0, 0, 0, 0, 1, 0, 0, 0, 0, 0, 0, 0, 0, 0, 1, 0, 1, 0, 0, 0, 0, 0, 0, 0, 0, 0, 0, 0, 0, 1, 0, 0, 0, 0, 0, 0, 0, 0, 0, 0, 0, 0, 0, 0, 0, 0, 0, 0, 0, 0, 0, 0, 0, 0, 0, 0, 0, 0, 0, 0, 0, 0, 0, 0, 0, 0, 0, 0, 0, 0, 0, 0, 0, 0, 0, 0, 0, 0, 0, 0, 0, 0, 0, 0, 0, 0, 0, 0, 0, 0, 0, 0, 0, 0, 0, 0, 0, 0, 0, 0, 0, 0, 0, 0, 0, 0, 0, 0, 0, 0, 0, 0, 0, 0, 0, 0, 1, 0, 0, 0, 0, 0, 0, 0, 0, 0, 0, 0, 0, 0, 0, 0, 0, 0, 0, 0, 0, 0, 0, 1, 0, 0, 0, 0, 0, 0, 0, 0, 0, 0, 0, 0, 0, 0, 0, 0, 0, 0, 0, 0, 0, 0, 0, 0, 0, 0, 0, 0, 0, 0, 0, 0, 0, 0, 0, 0, 0, 0, 0, 0, 0, 0, 0, 0, 0, 0, 0, 0, 0, 0, 1, 0, 0, 0, 0, 0, 0, 0, 0, 0, 0, 0, 0, 0, 0, 0, 0, 0, 0, 0, 0, 0, 0, 0, 0, 0, 0, 0, 0, 0, 0, 0, 0, 0, 0, 0, 0, 0, 0, 0, 0, 0, 0, 1, 0, 0, 0, 0, 0, 0, 0, 0, 0, 0, 0, 0, 0, 0, 0, 0, 0};
        h[2] = '{0, 0, 0, 0, 0, 0, 0, 0, 0, 0, 0, 0, 0, 0, 0, 0, 0, 0, 0, 0, 0, 0, 0, 1, 0, 0, 0, 0, 0, 0, 0, 0, 0, 0, 1, 1, 1, 0, 0, 0, 0, 0, 0, 0, 0, 0, 0, 0, 0, 0, 0, 0, 0, 0, 0, 0, 0, 0, 0, 0, 0, 0, 0, 0, 0, 0, 0, 0, 0, 0, 0, 0, 0, 0, 1, 0, 0, 0, 0, 0, 0, 0, 0, 0, 0, 0, 0, 0, 0, 0, 0, 0, 0, 0, 0, 0, 0, 0, 0, 0, 0, 0, 0, 0, 0, 0, 0, 0, 0, 0, 0, 0, 0, 0, 1, 0, 0, 0, 0, 0, 0, 0, 0, 0, 0, 0, 0, 0, 0, 0, 0, 0, 0, 0, 0, 0, 0, 0, 0, 0, 0, 0, 0, 0, 0, 0, 0, 0, 0, 0, 0, 0, 0, 0, 0, 0, 0, 0, 0, 0, 0, 0, 0, 0, 1, 0, 0, 0, 0, 0, 0, 0, 0, 0, 0, 0, 0, 0, 0, 0, 0, 0, 0, 0, 0, 0, 0, 0, 0, 0, 0, 0, 0, 1, 1, 0, 0, 0, 0, 0, 0, 0, 0, 0, 1, 0, 0, 0, 0, 0, 0, 0, 0, 0, 0, 0, 0, 0, 0, 0, 0, 0, 0, 0, 0, 0, 0, 0, 0, 0, 0, 0, 0, 0, 0, 0, 0, 0, 0, 0, 0, 0, 0, 0, 0, 0, 0, 0, 0, 0, 0, 0, 0, 0, 0, 0};
        h[3] = '{0, 0, 0, 0, 0, 0, 0, 0, 0, 0, 0, 0, 0, 0, 0, 0, 0, 0, 0, 0, 0, 0, 0, 0, 0, 0, 0, 0, 0, 0, 0, 0, 0, 0, 0, 0, 0, 0, 0, 0, 0, 0, 0, 0, 0, 0, 0, 0, 0, 0, 0, 0, 0, 0, 0, 0, 0, 0, 0, 0, 0, 0, 0, 0, 0, 0, 0, 0, 0, 0, 0, 0, 0, 0, 0, 0, 0, 0, 0, 0, 0, 0, 0, 0, 0, 0, 0, 0, 0, 0, 0, 0, 0, 0, 0, 0, 0, 0, 0, 0, 0, 0, 0, 0, 0, 0, 0, 1, 0, 0, 0, 0, 0, 0, 0, 0, 0, 0, 0, 0, 1, 0, 0, 0, 0, 0, 0, 0, 0, 0, 0, 0, 0, 0, 0, 0, 0, 0, 0, 0, 0, 0, 0, 0, 0, 0, 0, 0, 0, 0, 0, 0, 0, 0, 0, 0, 0, 0, 0, 0, 0, 0, 0, 0, 0, 0, 0, 0, 0, 0, 0, 0, 0, 0, 1, 0, 0, 0, 0, 1, 0, 0, 0, 0, 0, 0, 0, 0, 0, 0, 0, 0, 0, 0, 0, 0, 1, 0, 0, 0, 0, 0, 0, 0, 1, 0, 0, 0, 0, 1, 0, 0, 0, 0, 0, 0, 0, 0, 0, 0, 0, 0, 0, 0, 0, 0, 0, 0, 0, 0, 0, 0, 0, 0, 0, 0, 0, 0, 0, 0, 0, 0, 0, 0, 0, 0, 0, 0, 1, 0, 0, 0, 0, 0, 0, 0};
        h[4] = '{0, 0, 0, 0, 0, 0, 0, 0, 0, 0, 0, 0, 0, 0, 0, 0, 0, 0, 0, 0, 0, 0, 0, 0, 0, 0, 0, 0, 1, 0, 0, 0, 0, 0, 0, 0, 0, 0, 0, 0, 0, 0, 0, 0, 0, 0, 0, 0, 0, 0, 0, 0, 0, 0, 0, 0, 0, 0, 0, 0, 0, 0, 1, 0, 0, 0, 0, 0, 0, 0, 0, 0, 1, 0, 0, 0, 0, 0, 0, 0, 0, 0, 0, 0, 0, 0, 1, 0, 0, 0, 0, 1, 0, 0, 0, 0, 0, 0, 0, 0, 0, 0, 0, 0, 0, 0, 0, 0, 0, 0, 0, 0, 0, 0, 0, 0, 0, 0, 0, 0, 0, 0, 0, 0, 0, 0, 0, 0, 0, 0, 0, 0, 0, 0, 0, 0, 0, 0, 0, 0, 0, 0, 0, 0, 1, 0, 0, 0, 0, 0, 0, 0, 0, 0, 0, 0, 0, 0, 1, 0, 0, 0, 0, 0, 0, 0, 0, 0, 1, 0, 0, 0, 0, 0, 0, 0, 0, 0, 0, 0, 0, 0, 0, 0, 0, 0, 0, 0, 0, 1, 0, 0, 0, 0, 0, 0, 0, 0, 0, 0, 0, 0, 0, 0, 0, 0, 0, 0, 0, 0, 0, 0, 0, 0, 0, 0, 0, 0, 0, 0, 0, 0, 0, 0, 0, 0, 0, 0, 0, 0, 0, 0, 0, 0, 0, 0, 0, 0, 0, 0, 0, 0, 0, 0, 0, 0, 0, 0, 0, 0, 0, 0, 0, 0, 0, 0};
        h[5] = '{0, 0, 0, 1, 0, 0, 0, 0, 0, 0, 0, 0, 0, 0, 0, 0, 0, 0, 0, 0, 0, 1, 0, 0, 0, 0, 0, 0, 0, 0, 0, 0, 0, 0, 0, 0, 0, 0, 0, 0, 0, 0, 0, 0, 0, 0, 0, 0, 0, 0, 0, 0, 0, 0, 0, 0, 1, 0, 0, 0, 0, 0, 0, 0, 0, 0, 0, 0, 0, 0, 0, 0, 0, 0, 0, 0, 0, 0, 0, 0, 0, 0, 0, 0, 0, 0, 0, 0, 0, 0, 0, 0, 0, 0, 0, 0, 0, 0, 0, 0, 0, 0, 0, 0, 1, 0, 0, 0, 1, 0, 0, 0, 0, 0, 0, 0, 0, 0, 0, 0, 0, 0, 0, 0, 0, 0, 0, 0, 0, 0, 0, 0, 0, 0, 0, 0, 0, 0, 0, 0, 0, 0, 0, 0, 0, 0, 0, 0, 0, 0, 0, 0, 0, 0, 0, 0, 0, 0, 0, 0, 0, 0, 0, 0, 0, 0, 0, 0, 0, 0, 0, 0, 0, 0, 0, 0, 0, 0, 0, 0, 0, 0, 0, 0, 0, 0, 0, 0, 0, 0, 0, 0, 0, 0, 0, 0, 0, 1, 0, 0, 0, 0, 0, 0, 0, 0, 0, 0, 0, 0, 0, 0, 0, 0, 0, 0, 0, 0, 0, 0, 0, 0, 0, 0, 0, 0, 0, 0, 0, 0, 0, 0, 0, 0, 0, 0, 0, 0, 0, 0, 0, 0, 0, 0, 0, 0, 0, 0, 0, 0, 0, 0, 0, 0, 0, 0};
        h[6] = '{0, 0, 0, 0, 0, 0, 0, 0, 0, 0, 0, 0, 0, 0, 0, 0, 0, 0, 0, 0, 0, 0, 0, 0, 0, 0, 0, 0, 0, 0, 0, 0, 0, 0, 1, 0, 0, 0, 1, 0, 0, 0, 0, 0, 0, 0, 0, 0, 0, 0, 0, 0, 0, 0, 0, 0, 0, 0, 0, 0, 0, 0, 0, 0, 0, 0, 0, 0, 0, 0, 0, 0, 0, 0, 0, 0, 0, 0, 1, 0, 0, 0, 0, 0, 0, 0, 0, 0, 0, 0, 0, 0, 0, 0, 0, 0, 0, 0, 0, 0, 0, 0, 0, 0, 0, 0, 0, 1, 0, 0, 0, 0, 0, 0, 0, 0, 0, 0, 0, 0, 0, 0, 0, 0, 0, 0, 0, 0, 0, 0, 0, 0, 0, 1, 0, 0, 0, 0, 0, 0, 0, 0, 0, 0, 0, 0, 0, 0, 0, 0, 0, 0, 1, 0, 0, 0, 0, 0, 0, 0, 0, 0, 0, 0, 0, 0, 0, 0, 0, 0, 0, 0, 0, 0, 0, 0, 0, 0, 0, 1, 0, 0, 0, 0, 0, 0, 0, 0, 1, 0, 0, 0, 0, 0, 0, 0, 1, 0, 0, 0, 0, 0, 0, 0, 0, 1, 0, 0, 0, 0, 0, 0, 0, 1, 0, 0, 0, 0, 0, 0, 0, 0, 0, 0, 0, 0, 0, 0, 0, 0, 0, 0, 0, 0, 0, 0, 0, 0, 0, 0, 0, 0, 0, 0, 0, 0, 0, 0, 0, 0, 0, 0, 0, 0, 0, 0};
        h[7] = '{0, 0, 0, 0, 0, 0, 0, 0, 0, 0, 0, 0, 0, 0, 0, 0, 0, 0, 0, 0, 0, 0, 0, 0, 0, 0, 0, 0, 0, 0, 0, 0, 0, 0, 0, 0, 0, 0, 0, 0, 0, 0, 0, 0, 0, 0, 0, 0, 0, 0, 0, 0, 0, 0, 0, 1, 0, 0, 0, 0, 0, 0, 0, 0, 0, 0, 0, 0, 0, 0, 0, 0, 0, 0, 0, 0, 0, 0, 0, 0, 0, 0, 0, 0, 0, 0, 0, 0, 0, 1, 0, 0, 0, 0, 0, 0, 0, 0, 0, 0, 0, 0, 0, 0, 0, 0, 0, 0, 0, 0, 0, 0, 0, 1, 0, 0, 0, 0, 0, 0, 0, 0, 0, 0, 0, 0, 0, 0, 0, 0, 0, 0, 0, 0, 0, 0, 0, 0, 0, 0, 0, 0, 0, 0, 0, 0, 0, 0, 0, 0, 0, 0, 0, 0, 0, 0, 0, 0, 0, 0, 0, 0, 0, 0, 0, 0, 0, 0, 0, 0, 0, 0, 0, 0, 0, 0, 0, 0, 0, 1, 0, 0, 0, 0, 0, 0, 0, 0, 0, 0, 0, 0, 0, 0, 0, 0, 0, 0, 0, 0, 0, 0, 0, 0, 0, 0, 0, 0, 0, 0, 0, 0, 0, 0, 0, 0, 1, 0, 0, 0, 0, 0, 0, 0, 0, 0, 0, 0, 0, 0, 0, 0, 0, 0, 0, 0, 0, 0, 0, 1, 0, 0, 0, 0, 0, 0, 0, 0, 0, 0, 0, 0, 0, 0, 0, 0};
   
   
    
     #420;
     $finish;
    end

    always begin
        #0.1 clk = ~clk;
    end
    
    initial begin
        $dumpfile("HintBit.vcd");
        $dumpvars(0,HintBitPack_tb);
    end
           

endmodule

//clcok 2048 i=8 and j=256 ==>i*j=2048

ff2_part2_hintbitpack/ff2_part2_hintbitpack.sim/sim_1/behav/xsim/HintBit.vcd
$date
   Mon Feb 10 12:02:36 2025
$end
$version
  2018.2
$end
$timescale
  1ps
$end
$scope module HintBitPack_tb $end
$var reg 1 ! clk $end
$var reg 1 " rst $end
$var parameter 0 # K $end
$var parameter 0 $ COEFF_WIDTH $end
$var parameter 0 % W $end
$scope module uut $end
$var wire 1 & clk $end
$var wire 1 ' rst $end
$var reg 8 ( index [7:0] $end
$var reg 4 ) i [3:0] $end
$var reg 9 * j [8:0] $end
$var parameter 32 + K [31:0] $end
$var parameter 32 , W [31:0] $end
$var parameter 32 - COEFF_WIDTH [31:0] $end
$scope begin Block20_1 $end
$var reg 32 . i $end
$upscope $end
$upscope $end
$upscope $end
$enddefinitions $end
#0
$dumpvars
1!
1"
b1000 #
b100000000 $
b1001011 %
1&
1'
b0 (
b0 )
b0 *
b1000 +
b1001011 ,
b100000000 -
b1010011 .
$end
#100
0!
0&
#200
1!
1&
b1010011 .
#300
0!
0&
#400
1!
1&
b1010011 .
#500
0!
0&
#600
1!
1&
b1010011 .
#700
0!
0&
#800
1!
1&
b1010011 .
#900
0!
0&
#1000
1!
1&
b1010011 .
#1100
0!
0&
#1200
1!
1&
b1010011 .
#1300
0!
0&
#1400
1!
1&
b1010011 .
#1500
0!
0&
#1600
1!
1&
b1010011 .
#1700
0!
0&
#1800
1!
1&
b1010011 .
#1900
0!
0&
#2000
1!
1&
b1010011 .
#2100
0!
0&
#2200
1!
1&
b1010011 .
#2300
0!
0&
#2400
1!
1&
b1010011 .
#2500
0!
0&
#2600
1!
1&
b1010011 .
#2700
0!
0&
#2800
1!
1&
b1010011 .
#2900
0!
0&
#3000
1!
1&
b1010011 .
#3100
0!
0&
#3200
1!
1&
b1010011 .
#3300
0!
0&
#3400
1!
1&
b1010011 .
#3500
0!
0&
#3600
1!
1&
b1010011 .
#3700
0!
0&
#3800
1!
1&
b1010011 .
#3900
0!
0&
#4000
1!
1&
b1010011 .
#4100
0!
0&
#4200
1!
1&
b1010011 .
#4300
0!
0&
#4400
1!
1&
b1010011 .
#4500
0!
0&
#4600
1!
1&
b1010011 .
#4700
0!
0&
#4800
1!
1&
b1010011 .
#4900
0!
0&
#5000
1!
1&
b1010011 .
#5100
0!
0&
#5200
1!
1&
b1010011 .
#5300
0!
0&
#5400
1!
1&
b1010011 .
#5500
0!
0&
#5600
1!
1&
b1010011 .
#5700
0!
0&
#5800
1!
1&
b1010011 .
#5900
0!
0&
#6000
1!
1&
b1010011 .
#6100
0!
0&
#6200
1!
1&
b1010011 .
#6300
0!
0&
#6400
1!
1&
b1010011 .
#6500
0!
0&
#6600
1!
1&
b1010011 .
#6700
0!
0&
#6800
1!
1&
b1010011 .
#6900
0!
0&
#7000
1!
1&
b1010011 .
#7100
0!
0&
#7200
1!
1&
b1010011 .
#7300
0!
0&
#7400
1!
1&
b1010011 .
#7500
0!
0&
#7600
1!
1&
b1010011 .
#7700
0!
0&
#7800
1!
1&
b1010011 .
#7900
0!
0&
#8000
1!
1&
b1010011 .
#8100
0!
0&
#8200
1!
1&
b1010011 .
#8300
0!
0&
#8400
1!
1&
b1010011 .
#8500
0!
0&
#8600
1!
1&
b1010011 .
#8700
0!
0&
#8800
1!
1&
b1010011 .
#8900
0!
0&
#9000
1!
1&
b1010011 .
#9100
0!
0&
#9200
1!
1&
b1010011 .
#9300
0!
0&
#9400
1!
1&
b1010011 .
#9500
0!
0&
#9600
1!
1&
b1010011 .
#9700
0!
0&
#9800
1!
1&
b1010011 .
#9900
0!
0&
#10000
1!
0"
1&
0'
b1 *
#10100
0!
0&
#10200
1!
1&
b10 *
#10300
0!
0&
#10400
1!
1&
b11 *
#10500
0!
0&
#10600
1!
1&
b100 *
#10700
0!
0&
#10800
1!
1&
b101 *
#10900
0!
0&
#11000
1!
1&
b1 (
b110 *
#11100
0!
0&
#11200
1!
1&
b111 *
#11300
0!
0&
#11400
1!
1&
b1000 *
#11500
0!
0&
#11600
1!
1&
b1001 *
#11700
0!
0&
#11800
1!
1&
b1010 *
#11900
0!
0&
#12000
1!
1&
b1011 *
#12100
0!
0&
#12200
1!
1&
b1100 *
#12300
0!
0&
#12400
1!
1&
b1101 *
#12500
0!
0&
#12600
1!
1&
b1110 *
#12700
0!
0&
#12800
1!
1&
b1111 *
#12900
0!
0&
#13000
1!
1&
b10000 *
#13100
0!
0&
#13200
1!
1&
b10001 *
#13300
0!
0&
#13400
1!
1&
b10010 *
#13500
0!
0&
#13600
1!
1&
b10011 *
#13700
0!
0&
#13800
1!
1&
b10100 *
#13900
0!
0&
#14000
1!
1&
b10101 *
#14100
0!
0&
#14200
1!
1&
b10110 *
#14300
0!
0&
#14400
1!
1&
b10111 *
#14500
0!
0&
#14600
1!
1&
b11000 *
#14700
0!
0&
#14800
1!
1&
b11001 *
#14900
0!
0&
#15000
1!
1&
b11010 *
#15100
0!
0&
#15200
1!
1&
b11011 *
#15300
0!
0&
#15400
1!
1&
b11100 *
#15500
0!
0&
#15600
1!
1&
b11101 *
#15700
0!
0&
#15800
1!
1&
b11110 *
#15900
0!
0&
#16000
1!
1&
b11111 *
#16100
0!
0&
#16200
1!
1&
b100000 *
#16300
0!
0&
#16400
1!
1&
b100001 *
#16500
0!
0&
#16600
1!
1&
b100010 *
#16700
0!
0&
#16800
1!
1&
b100011 *
#16900
0!
0&
#17000
1!
1&
b100100 *
#17100
0!
0&
#17200
1!
1&
b100101 *
#17300
0!
0&
#17400
1!
1&
b100110 *
#17500
0!
0&
#17600
1!
1&
b100111 *
#17700
0!
0&
#17800
1!
1&
b101000 *
#17900
0!
0&
#18000
1!
1&
b101001 *
#18100
0!
0&
#18200
1!
1&
b101010 *
#18300
0!
0&
#18400
1!
1&
b101011 *
#18500
0!
0&
#18600
1!
1&
b101100 *
#18700
0!
0&
#18800
1!
1&
b101101 *
#18900
0!
0&
#19000
1!
1&
b101110 *
#19100
0!
0&
#19200
1!
1&
b101111 *
#19300
0!
0&
#19400
1!
1&
b110000 *
#19500
0!
0&
#19600
1!
1&
b110001 *
#19700
0!
0&
#19800
1!
1&
b110010 *
#19900
0!
0&
#20000
1!
1&
b110011 *
#20100
0!
0&
#20200
1!
1&
b110100 *
#20300
0!
0&
#20400
1!
1&
b110101 *
#20500
0!
0&
#20600
1!
1&
b110110 *
#20700
0!
0&
#20800
1!
1&
b110111 *
#20900
0!
0&
#21000
1!
1&
b111000 *
#21100
0!
0&
#21200
1!
1&
b111001 *
#21300
0!
0&
#21400
1!
1&
b111010 *
#21500
0!
0&
#21600
1!
1&
b111011 *
#21700
0!
0&
#21800
1!
1&
b111100 *
#21900
0!
0&
#22000
1!
1&
b111101 *
#22100
0!
0&
#22200
1!
1&
b111110 *
#22300
0!
0&
#22400
1!
1&
b111111 *
#22500
0!
0&
#22600
1!
1&
b1000000 *
