entropy/entropy.srcs/sources_1/new/ringOscillator.sv
`timescale 1ns / 1ps
//////////////////////////////////////////////////////////////////////////////////
// Company: 
// Engineer: 
// 
// Create Date: 30.03.2025 05:55:00
// Design Name: 
// Module Name: ringOscillator
// Project Name: 
// Target Devices: 
// Tool Versions: 
// Description: 
// 
// Dependencies: 
// 
// Revision:
// Revision 0.01 - File Created
// Additional Comments:
// 
//////////////////////////////////////////////////////////////////////////////////


module ring_oscillator #(parameter int N = 3) (
    input logic rst,clk,       // Active-high reset
//    input logic bin,       // Single-bit input (0 or 1)
    output logic out       // Oscillating output
);
    logic [N-1:0] inv;

    always_ff @(posedge rst or posedge clk) begin
        if (rst)
            inv <= 0; // Initialize all bits to the input value
        else
            inv <= {inv[N-2:0], ~inv[N-1]}; // Shift and invert
    end

    assign out = inv[N-1]; // Output last inverter value
endmodule

entropy/entropy.srcs/sources_1/new/ringOscillatorTop.sv
`timescale 1ns / 1ps
//////////////////////////////////////////////////////////////////////////////////
// Company: 
// Engineer: 
// 
// Create Date: 30.03.2025 05:58:07
// Design Name: 
// Module Name: ringOscillatorTop
// Project Name: 
// Target Devices: 
// Tool Versions: 
// Description: 
// 
// Dependencies: 
// 
// Revision:
// Revision 0.01 - File Created
// Additional Comments:
// 
//////////////////////////////////////////////////////////////////////////////////


module ringOscillatorTop (
    input logic clk,               // System clock (for sampling)
    input logic rst,               // Active-high reset
    output logic rand_xor           // XORed single-bit output
);
    // 8 Ring Oscillators (each with a unique length)
    logic ro_out[7:0]; 

    // Instantiate 8 different ring oscillators with clk and rst
    ring_oscillator #(3) ro1 (.clk(clk), .rst(rst), .out(ro_out[0]));
    ring_oscillator #(5) ro2 (.clk(clk), .rst(rst), .out(ro_out[1]));
    ring_oscillator #(7) ro3 (.clk(clk), .rst(rst), .out(ro_out[2]));
    ring_oscillator #(9) ro4 (.clk(clk), .rst(rst), .out(ro_out[3]));
    ring_oscillator #(11) ro5 (.clk(clk), .rst(rst), .out(ro_out[4]));
    ring_oscillator #(13) ro6 (.clk(clk), .rst(rst), .out(ro_out[5]));
    ring_oscillator #(15) ro7 (.clk(clk), .rst(rst), .out(ro_out[6]));
    ring_oscillator #(17) ro8 (.clk(clk), .rst(rst), .out(ro_out[7]));

    always_ff @(posedge clk or posedge rst) begin
        if (rst) begin
            rand_xor <= 1'b0;
        end else begin

            // XORed output for randomness
            rand_xor <= ro_out[0] ^ ro_out[1] ^ ro_out[2] ^ ro_out[3] ^ 
                        ro_out[4] ^ ro_out[5] ^ ro_out[6] ^ ro_out[7];
        end
    end
endmodule

entropy/entropy.srcs/sources_1/new/ringOscillatorTop_tb.sv
`timescale 1ns / 1ps
//////////////////////////////////////////////////////////////////////////////////
// Company: 
// Engineer: 
// 
// Create Date: 30.03.2025 06:09:01
// Design Name: 
// Module Name: ringOscillatorTop_tb
// Project Name: 
// Target Devices: 
// Tool Versions: 
// Description: 
// 
// Dependencies: 
// 
// Revision:
// Revision 0.01 - File Created
// Additional Comments:
// 
//////////////////////////////////////////////////////////////////////////////////


`timescale 1ns / 1ps

module ringOscillatorTop_tb;

    logic clk, rst;
    logic rand_xor;

    // Instantiate the DUT (SanityCheck module)
    ringOscillatorTop dut (
        .clk(clk),
        .rst(rst),
        .rand_xor(rand_xor)
    );

    // Initialize Test
    initial begin
        int i, j;  // Declare loop variables inside the initial block

        $display("Starting Sanity Check Testbench...");
        clk = 0;
        rst = 1;
        #10;
        rst = 0;
        #20
        $finish;
        end
        
       always begin
                #0.1 clk = ~clk;
            end
            
            initial begin
                $dumpfile("ringOscillatorTop_tb.vcd");
                $dumpvars(0,ringOscillatorTop_tb);
            end
        
      
endmodule

entropy/entropy.sim/sim_1/behav/xsim/ringOscillatorTop_tb.vcd
$date
   Sun Mar 30 06:42:57 2025
$end
$version
  2018.2
$end
$timescale
  1ps
$end
$scope module ringOscillatorTop_tb $end
$var reg 1 ! clk $end
$var reg 1 " rst $end
$var reg 1 # rand_xor $end
$scope module dut $end
$var wire 1 $ clk $end
$var wire 1 % rst $end
$var reg 1 # rand_xor $end
$scope module ro1 $end
$var wire 1 % rst $end
$var wire 1 $ clk $end
$var reg 1 & out $end
$var reg 3 ' inv [2:0] $end
$var parameter 0 ( N $end
$upscope $end
$scope module ro2 $end
$var wire 1 % rst $end
$var wire 1 $ clk $end
$var reg 1 ) out $end
$var reg 5 * inv [4:0] $end
$var parameter 0 + N $end
$upscope $end
$scope module ro3 $end
$var wire 1 % rst $end
$var wire 1 $ clk $end
$var reg 1 , out $end
$var reg 7 - inv [6:0] $end
$var parameter 0 . N $end
$upscope $end
$scope module ro4 $end
$var wire 1 % rst $end
$var wire 1 $ clk $end
$var reg 1 / out $end
$var reg 9 0 inv [8:0] $end
$var parameter 0 1 N $end
$upscope $end
$scope module ro5 $end
$var wire 1 % rst $end
$var wire 1 $ clk $end
$var reg 1 2 out $end
$var reg 11 3 inv [10:0] $end
$var parameter 0 4 N $end
$upscope $end
$scope module ro6 $end
$var wire 1 % rst $end
$var wire 1 $ clk $end
$var reg 1 5 out $end
$var reg 13 6 inv [12:0] $end
$var parameter 0 7 N $end
$upscope $end
$scope module ro7 $end
$var wire 1 % rst $end
$var wire 1 $ clk $end
$var reg 1 8 out $end
$var reg 15 9 inv [14:0] $end
$var parameter 0 : N $end
$upscope $end
$scope module ro8 $end
$var wire 1 % rst $end
$var wire 1 $ clk $end
$var reg 1 ; out $end
$var reg 17 < inv [16:0] $end
$var parameter 0 = N $end
$upscope $end
$upscope $end
$scope begin Block38_10 $end
$var reg 32 > i $end
$var reg 32 ? j $end
$upscope $end
$upscope $end
$enddefinitions $end
#0
$dumpvars
0!
1"
0#
0$
1%
0&
b0 '
b11 (
0)
b0 *
b101 +
0,
b0 -
b111 .
0/
b0 0
b1001 1
02
b0 3
b1011 4
05
b0 6
b1101 7
08
b0 9
b1111 :
0;
b0 <
b10001 =
b0 >
b0 ?
$end
#100
1!
1$
#200
0!
0$
#300
1!
1$
#400
0!
0$
#500
1!
1$
#600
0!
0$
#700
1!
1$
#800
0!
0$
#900
1!
1$
#1000
0!
0$
#1100
1!
1$
#1200
0!
0$
#1300
1!
1$
#1400
0!
0$
#1500
1!
1$
#1600
0!
0$
#1700
1!
1$
#1800
0!
0$
#1900
1!
1$
#2000
0!
0$
#2100
1!
1$
#2200
0!
0$
#2300
1!
1$
#2400
0!
0$
#2500
1!
1$
#2600
0!
0$
#2700
1!
1$
#2800
0!
0$
#2900
1!
1$
#3000
0!
0$
#3100
1!
1$
#3200
0!
0$
#3300
1!
1$
#3400
0!
0$
#3500
1!
1$
#3600
0!
0$
#3700
1!
1$
#3800
0!
0$
#3900
1!
1$
#4000
0!
0$
#4100
1!
1$
#4200
0!
0$
#4300
1!
1$
#4400
0!
0$
#4500
1!
1$
#4600
0!
0$
#4700
1!
1$
#4800
0!
0$
#4900
1!
1$
#5000
0!
0$
#5100
1!
1$
#5200
0!
0$
#5300
1!
1$
#5400
0!
0$
#5500
1!
1$
#5600
0!
0$
#5700
1!
1$
#5800
0!
0$
#5900
1!
1$
#6000
0!
0$
#6100
1!
1$
#6200
0!
0$
#6300
1!
1$
#6400
0!
0$
#6500
1!
1$
#6600
0!
0$
#6700
1!
1$
#6800
0!
0$
#6900
1!
1$
#7000
0!
0$
#7100
1!
1$
#7200
0!
0$
#7300
1!
1$
#7400
0!
0$
#7500
1!
1$
#7600
0!
0$
#7700
1!
1$
#7800
0!
0$
#7900
1!
1$
#8000
0!
0$
#8100
1!
1$
#8200
0!
0$
#8300
1!
1$
#8400
0!
0$
#8500
1!
1$
#8600
0!
0$
#8700
1!
1$
#8800
0!
0$
#8900
1!
1$
#9000
0!
0$
#9100
1!
1$
#9200
0!
0$
#9300
1!
1$
#9400
0!
0$
#9500
1!
1$
#9600
0!
0$
#9700
1!
1$
#9800
0!
0$
#9900
1!
1$
#10000
0!
0"
0$
0%
#10100
1!
1$
b1 '
b1 *
b1 -
b1 0
b1 3
b1 6
b1 9
b1 <
#10200
0!
0$
#10300
1!
1$
b11 '
b11 *
b11 -
b11 0
b11 3
b11 6
b11 9
b11 <
#10400
0!
0$
#10500
1!
1$
1&
b111 '
b111 *
b111 -
b111 0
b111 3
b111 6
b111 9
b111 <
#10600
0!
0$
#10700
1!
1#
1$
b110 '
b1111 *
b1111 -
b1111 0
b1111 3
b1111 6
b1111 9
b1111 <
#10800
0!
0$
#10900
1!
1$
b100 '
1)
b11111 *
b11111 -
b11111 0
b11111 3
b11111 6
b11111 9
b11111 <
#11000
0!
0$
#11100
1!
0#
1$
0&
b0 '
b11110 *
b111111 -
b111111 0
b111111 3
b111111 6
b111111 9
b111111 <
#11200
0!
0$
#11300
1!
1#
1$
b1 '
b11100 *
1,
b1111111 -
b1111111 0
b1111111 3
b1111111 6
b1111111 9
b1111111 <
#11400
0!
0$
#11500
1!
0#
1$
b11 '
b11000 *
b1111110 -
b11111111 0
b11111111 3
b11111111 6
b11111111 9
b11111111 <
#11600
0!
0$
#11700
1!
1$
1&
b111 '
b10000 *
b1111100 -
1/
b111111111 0
b111111111 3
b111111111 6
b111111111 9
b111111111 <
#11800
0!
0$
#11900
1!
1$
b110 '
0)
b0 *
b1111000 -
b111111110 0
b1111111111 3
b1111111111 6
b1111111111 9
b1111111111 <
#12000
0!
0$
#12100
1!
1#
1$
b100 '
b1 *
b1110000 -
b111111100 0
12
b11111111111 3
b11111111111 6
b11111111111 9
b11111111111 <
#12200
0!
0$
#12300
1!
0#
1$
0&
b0 '
b11 *
b1100000 -
b111111000 0
b11111111110 3
b111111111111 6
b111111111111 9
b111111111111 <
#12400
0!
0$
#12500
1!
1#
1$
b1 '
b111 *
b1000000 -
b111110000 0
b11111111100 3
15
b1111111111111 6
b1111111111111 9
b1111111111111 <
#12600
0!
0$
#12700
1!
0#
1$
b11 '
b1111 *
0,
b0 -
b111100000 0
b11111111000 3
b1111111111110 6
b11111111111111 9
b11111111111111 <
#12800
0!
0$
#12900
1!
1#
1$
1&
b111 '
1)
b11111 *
b1 -
b111000000 0
b11111110000 3
b1111111111100 6
18
b111111111111111 9
b111111111111111 <
#13000
0!
0$
#13100
1!
0#
1$
b110 '
b11110 *
b11 -
b110000000 0
b11111100000 3
b1111111111000 6
b111111111111110 9
b1111111111111111 <
#13200
0!
0$
#13300
1!
1$
b100 '
b11100 *
b111 -
b100000000 0
b11111000000 3
b1111111110000 6
b111111111111100 9
1;
b11111111111111111 <
#13400
0!
0$
#13500
1!
1#
1$
0&
b0 '
b11000 *
b1111 -
0/
b0 0
b11110000000 3
b1111111100000 6
b111111111111000 9
b11111111111111110 <
#13600
0!
0$
#13700
1!
1$
b1 '
b10000 *
b11111 -
b1 0
b11100000000 3
b1111111000000 6
b111111111110000 9
b11111111111111100 <
#13800
0!
0$
#13900
1!
1$
b11 '
0)
b0 *
b111111 -
b11 0
b11000000000 3
b1111110000000 6
b111111111100000 9
b11111111111111000 <
#14000
0!
0$
#14100
1!
0#
1$
1&
b111 '
b1 *
1,
b1111111 -
b111 0
b10000000000 3
b1111100000000 6
b111111111000000 9
b11111111111110000 <
#14200
0!
0$
#14300
1!
1$
b110 '
b11 *
b1111110 -
b1111 0
02
b0 3
b1111000000000 6
b111111110000000 9
b11111111111100000 <
#14400
0!
0$
#14500
1!
1#
1$
b100 '
b111 *
b1111100 -
b11111 0
b1 3
b1110000000000 6
b111111100000000 9
b11111111111000000 <
#14600
0!
0$
#14700
1!
1$
0&
b0 '
b1111 *
b1111000 -
b111111 0
b11 3
b1100000000000 6
b111111000000000 9
b11111111110000000 <
#14800
0!
0$
#14900
1!
0#
1$
b1 '
1)
b11111 *
b1110000 -
b1111111 0
b111 3
b1000000000000 6
b111110000000000 9
b11111111100000000 <
#15000
0!
0$
#15100
1!
1#
1$
b11 '
b11110 *
b1100000 -
b11111111 0
b1111 3
05
b0 6
b111100000000000 9
b11111111000000000 <
#15200
0!
0$
#15300
1!
0#
1$
1&
b111 '
b11100 *
b1000000 -
1/
b111111111 0
b11111 3
b1 6
b111000000000000 9
b11111110000000000 <
#15400
0!
0$
#15500
1!
1$
b110 '
b11000 *
0,
b0 -
b111111110 0
b111111 3
b11 6
b110000000000000 9
b11111100000000000 <
#15600
0!
0$
#15700
1!
1#
1$
b100 '
b10000 *
b1 -
b111111100 0
b1111111 3
b111 6
b100000000000000 9
b11111000000000000 <
#15800
0!
0$
#15900
1!
1$
0&
b0 '
0)
b0 *
b11 -
b111111000 0
b11111111 3
b1111 6
08
b0 9
b11110000000000000 <
#16000
0!
0$
#16100
1!
0#
1$
b1 '
b1 *
b111 -
b111110000 0
b111111111 3
b11111 6
b1 9
b11100000000000000 <
#16200
0!
0$
#16300
1!
1$
b11 '
b11 *
b1111 -
b111100000 0
b1111111111 3
b111111 6
b11 9
b11000000000000000 <
#16400
0!
0$
#16500
1!
1$
1&
b111 '
b111 *
b11111 -
b111000000 0
12
b11111111111 3
b1111111 6
b111 9
b10000000000000000 <
#16600
0!
0$
#16700
1!
1$
b110 '
b1111 *
b111111 -
b110000000 0
b11111111110 3
b11111111 6
b1111 9
0;
b0 <
#16800
0!
0$
#16900
1!
1#
1$
b100 '
1)
b11111 *
1,
b1111111 -
b100000000 0
b11111111100 3
b111111111 6
b11111 9
b1 <
#17000
0!
0$
#17100
1!
1$
0&
b0 '
b11110 *
b1111110 -
0/
b0 0
b11111111000 3
b1111111111 6
b111111 9
b11 <
#17200
0!
0$
#17300
1!
1$
b1 '
b11100 *
b1111100 -
b1 0
b11111110000 3
b11111111111 6
b1111111 9
b111 <
#17400
0!
0$
#17500
1!
1$
b11 '
b11000 *
b1111000 -
b11 0
b11111100000 3
b111111111111 6
b11111111 9
b1111 <
#17600
0!
0$
#17700
1!
1$
1&
b111 '
b10000 *
b1110000 -
b111 0
b11111000000 3
15
b1111111111111 6
b111111111 9
b11111 <
#17800
0!
0$
#17900
1!
1$
b110 '
0)
b0 *
b1100000 -
b1111 0
b11110000000 3
b1111111111110 6
b1111111111 9
b111111 <
#18000
0!
0$
#18100
1!
0#
1$
b100 '
b1 *
b1000000 -
b11111 0
b11100000000 3
b1111111111100 6
b11111111111 9
b1111111 <
#18200
0!
0$
#18300
1!
1$
0&
b0 '
b11 *
0,
b0 -
b111111 0
b11000000000 3
b1111111111000 6
b111111111111 9
b11111111 <
#18400
0!
0$
#18500
1!
1$
b1 '
b111 *
b1 -
b1111111 0
b10000000000 3
b1111111110000 6
b1111111111111 9
b111111111 <
#18600
0!
0$
#18700
1!
1$
b11 '
b1111 *
b11 -
b11111111 0
02
b0 3
b1111111100000 6
b11111111111111 9
b1111111111 <
#18800
0!
0$
#18900
1!
1#
1$
1&
b111 '
1)
b11111 *
b111 -
1/
b111111111 0
b1 3
b1111111000000 6
18
b111111111111111 9
b11111111111 <
#19000
0!
0$
#19100
1!
1$
b110 '
b11110 *
b1111 -
b111111110 0
b11 3
b1111110000000 6
b111111111111110 9
b111111111111 <
#19200
0!
0$
#19300
1!
1$
b100 '
b11100 *
b11111 -
b111111100 0
b111 3
b1111100000000 6
b111111111111100 9
b1111111111111 <
#19400
0!
0$
#19500
1!
1$
0&
b0 '
b11000 *
b111111 -
b111111000 0
b1111 3
b1111000000000 6
b111111111111000 9
b11111111111111 <
#19600
0!
0$
#19700
1!
0#
1$
b1 '
b10000 *
1,
b1111111 -
b111110000 0
b11111 3
b1110000000000 6
b111111111110000 9
b111111111111111 <
#19800
0!
0$
#19900
1!
1#
1$
b11 '
0)
b0 *
b1111110 -
b111100000 0
b111111 3
b1100000000000 6
b111111111100000 9
b1111111111111111 <
#20000
0!
0$
#20100
1!
0#
1$
1&
b111 '
b1 *
b1111100 -
b111000000 0
b1111111 3
b1000000000000 6
b111111111000000 9
1;
b11111111111111111 <
#20200
0!
0$
#20300
1!
1$
b110 '
b11 *
b1111000 -
b110000000 0
b11111111 3
05
b0 6
b111111110000000 9
b11111111111111110 <
#20400
0!
0$
#20500
1!
1#
1$
b100 '
b111 *
b1110000 -
b100000000 0
b111111111 3
b1 6
b111111100000000 9
b11111111111111100 <
#20600
0!
0$
#20700
1!
1$
0&
b0 '
b1111 *
b1100000 -
0/
b0 0
b1111111111 3
b11 6
b111111000000000 9
b11111111111111000 <
#20800
0!
0$
#20900
1!
1$
b1 '
1)
b11111 *
b1000000 -
b1 0
12
b11111111111 3
b111 6
b111110000000000 9
b11111111111110000 <
#21000
0!
0$
#21100
1!
1$
b11 '
b11110 *
0,
b0 -
b11 0
b11111111110 3
b1111 6
b111100000000000 9
b11111111111100000 <
#21200
0!
0$
#21300
1!
0#
1$
1&
b111 '
b11100 *
b1 -
b111 0
b11111111100 3
b11111 6
b111000000000000 9
b11111111111000000 <
#21400
0!
0$
#21500
1!
1#
1$
b110 '
b11000 *
b11 -
b1111 0
b11111111000 3
b111111 6
b110000000000000 9
b11111111110000000 <
#21600
0!
0$
#21700
1!
1$
b100 '
b10000 *
b111 -
b11111 0
b11111110000 3
b1111111 6
b100000000000000 9
b11111111100000000 <
#21800
0!
0$
#21900
1!
1$
0&
b0 '
0)
b0 *
b1111 -
b111111 0
b11111100000 3
b11111111 6
08
b0 9
b11111111000000000 <
#22000
0!
0$
#22100
1!
0#
1$
b1 '
b1 *
b11111 -
b1111111 0
b11111000000 3
b111111111 6
b1 9
b11111110000000000 <
#22200
0!
0$
#22300
1!
1$
b11 '
b11 *
b111111 -
b11111111 0
b11110000000 3
b1111111111 6
b11 9
b11111100000000000 <
#22400
0!
0$
#22500
1!
1$
1&
b111 '
b111 *
1,
b1111111 -
1/
b111111111 0
b11100000000 3
b11111111111 6
b111 9
b11111000000000000 <
#22600
0!
0$
#22700
1!
1#
1$
b110 '
b1111 *
b1111110 -
b111111110 0
b11000000000 3
b111111111111 6
b1111 9
b11110000000000000 <
#22800
0!
0$
#22900
1!
1$
b100 '
1)
b11111 *
b1111100 -
b111111100 0
b10000000000 3
15
b1111111111111 6
b11111 9
b11100000000000000 <
#23000
0!
0$
#23100
1!
1$
0&
b0 '
b11110 *
b1111000 -
b111111000 0
02
b0 3
b1111111111110 6
b111111 9
b11000000000000000 <
#23200
0!
0$
#23300
1!
1$
b1 '
b11100 *
b1110000 -
b111110000 0
b1 3
b1111111111100 6
b1111111 9
b10000000000000000 <
#23400
0!
0$
#23500
1!
1$
b11 '
b11000 *
b1100000 -
b111100000 0
b11 3
b1111111111000 6
b11111111 9
0;
b0 <
#23600
0!
0$
#23700
1!
0#
1$
1&
b111 '
b10000 *
b1000000 -
b111000000 0
b111 3
b1111111110000 6
b111111111 9
b1 <
#23800
0!
0$
#23900
1!
1#
1$
b110 '
0)
b0 *
0,
b0 -
b110000000 0
b1111 3
b1111111100000 6
b1111111111 9
b11 <
#24000
0!
0$
#24100
1!
1$
b100 '
b1 *
b1 -
b100000000 0
b11111 3
b1111111000000 6
b11111111111 9
b111 <
#24200
0!
0$
#24300
1!
1$
0&
b0 '
b11 *
b11 -
0/
b0 0
b111111 3
b1111110000000 6
b111111111111 9
b1111 <
#24400
0!
0$
#24500
1!
1$
b1 '
b111 *
b111 -
b1 0
b1111111 3
b1111100000000 6
b1111111111111 9
b11111 <
#24600
0!
0$
#24700
1!
1$
b11 '
b1111 *
b1111 -
b11 0
b11111111 3
b1111000000000 6
b11111111111111 9
b111111 <
#24800
0!
0$
#24900
1!
1$
1&
b111 '
1)
b11111 *
b11111 -
b111 0
b111111111 3
b1110000000000 6
18
b111111111111111 9
b1111111 <
#25000
0!
0$
#25100
1!
0#
1$
b110 '
b11110 *
b111111 -
b1111 0
b1111111111 3
b1100000000000 6
b111111111111110 9
b11111111 <
#25200
0!
0$
#25300
1!
1$
b100 '
b11100 *
1,
b1111111 -
b11111 0
12
b11111111111 3
b1000000000000 6
b111111111111100 9
b111111111 <
#25400
0!
0$
#25500
1!
1$
0&
b0 '
b11000 *
b1111110 -
b111111 0
b11111111110 3
05
b0 6
b111111111111000 9
b1111111111 <
#25600
0!
0$
#25700
1!
1$
b1 '
b10000 *
b1111100 -
b1111111 0
b11111111100 3
b1 6
b111111111110000 9
b11111111111 <
#25800
0!
0$
#25900
1!
1$
b11 '
0)
b0 *
b1111000 -
b11111111 0
b11111111000 3
b11 6
b111111111100000 9
b111111111111 <
#26000
0!
0$
#26100
1!
1#
1$
1&
b111 '
b1 *
b1110000 -
1/
b111111111 0
b11111110000 3
b111 6
b111111111000000 9
b1111111111111 <
#26200
0!
0$
#26300
1!
1$
b110 '
b11 *
b1100000 -
b111111110 0
b11111100000 3
b1111 6
b111111110000000 9
b11111111111111 <
#26400
0!
0$
#26500
1!
1$
b100 '
b111 *
b1000000 -
b111111100 0
b11111000000 3
b11111 6
b111111100000000 9
b111111111111111 <
#26600
0!
0$
#26700
1!
1$
0&
b0 '
b1111 *
0,
b0 -
b111111000 0
b11110000000 3
b111111 6
b111111000000000 9
b1111111111111111 <
#26800
0!
0$
#26900
1!
1$
b1 '
1)
b11111 *
b1 -
b111110000 0
b11100000000 3
b1111111 6
b111110000000000 9
1;
b11111111111111111 <
#27000
0!
0$
#27100
1!
1$
b11 '
b11110 *
b11 -
b111100000 0
b11000000000 3
b11111111 6
b111100000000000 9
b11111111111111110 <
#27200
0!
0$
#27300
1!
1$
1&
b111 '
b11100 *
b111 -
b111000000 0
b10000000000 3
b111111111 6
b111000000000000 9
b11111111111111100 <
#27400
0!
0$
#27500
1!
0#
1$
b110 '
b11000 *
b1111 -
b110000000 0
02
b0 3
b1111111111 6
b110000000000000 9
b11111111111111000 <
#27600
0!
0$
#27700
1!
1#
1$
b100 '
b10000 *
b11111 -
b100000000 0
b1 3
b11111111111 6
b100000000000000 9
b11111111111110000 <
#27800
0!
0$
#27900
1!
1$
0&
b0 '
0)
b0 *
b111111 -
0/
b0 0
b11 3
b111111111111 6
08
b0 9
b11111111111100000 <
#28000
0!
0$
#28100
1!
1$
b1 '
b1 *
1,
b1111111 -
b1 0
b111 3
15
b1111111111111 6
b1 9
b11111111111000000 <
#28200
0!
0$
#28300
1!
1$
b11 '
b11 *
b1111110 -
b11 0
b1111 3
b1111111111110 6
b11 9
b11111111110000000 <
#28400
0!
0$
#28500
1!
1$
1&
b111 '
b111 *
b1111100 -
b111 0
b11111 3
b1111111111100 6
b111 9
b11111111100000000 <
#28600
0!
0$
#28700
1!
0#
1$
b110 '
b1111 *
b1111000 -
b1111 0
b111111 3
b1111111111000 6
b1111 9
b11111111000000000 <
#28800
0!
0$
#28900
1!
1$
b100 '
1)
b11111 *
b1110000 -
b11111 0
b1111111 3
b1111111110000 6
b11111 9
b11111110000000000 <
#29000
0!
0$
#29100
1!
1#
1$
0&
b0 '
b11110 *
b1100000 -
b111111 0
b11111111 3
b1111111100000 6
b111111 9
b11111100000000000 <
#29200
0!
0$
#29300
1!
0#
1$
b1 '
b11100 *
b1000000 -
b1111111 0
b111111111 3
b1111111000000 6
b1111111 9
b11111000000000000 <
#29400
0!
0$
#29500
1!
1$
b11 '
b11000 *
0,
b0 -
b11111111 0
b1111111111 3
b1111110000000 6
b11111111 9
b11110000000000000 <
#29600
0!
0$
#29700
1!
1#
1$
1&
b111 '
b10000 *
b1 -
1/
b111111111 0
12
b11111111111 3
b1111100000000 6
b111111111 9
b11100000000000000 <
